test.py
OpenSTRAN/Menu.py
OpenSTRAN/__init__.py
OpenSTRAN/mainScreen.py
OpenSTRAN/model.py
OpenSTRAN/__pycache__/Menu.cpython-310.pyc
OpenSTRAN/__pycache__/__init__.cpython-310.pyc
OpenSTRAN/__pycache__/mainScreen.cpython-310.pyc
OpenSTRAN/__pycache__/model.cpython-310.pyc
OpenSTRAN/fem/Coordinates.py
OpenSTRAN/fem/Member.py
OpenSTRAN/fem/Members.py
OpenSTRAN/fem/Model.py
OpenSTRAN/fem/Node.py
OpenSTRAN/fem/Nodes.py
OpenSTRAN/fem/Plotter.py
OpenSTRAN/fem/Solver.py
OpenSTRAN/fem/Submember.py
OpenSTRAN/fem/__init__.py
OpenSTRAN/fem/__pycache__/Coordinates.cpython-310.pyc
OpenSTRAN/fem/__pycache__/Member.cpython-310.pyc
OpenSTRAN/fem/__pycache__/Members.cpython-310.pyc
OpenSTRAN/fem/__pycache__/Model.cpython-310.pyc
OpenSTRAN/fem/__pycache__/Node.cpython-310.pyc
OpenSTRAN/fem/__pycache__/Nodes.cpython-310.pyc
OpenSTRAN/fem/__pycache__/Plotter.cpython-310.pyc
OpenSTRAN/fem/__pycache__/Solver.cpython-310.pyc
OpenSTRAN/fem/__pycache__/Submember.cpython-310.pyc
OpenSTRAN/fem/__pycache__/__init__.cpython-310.pyc
OpenSTRAN/projectFiles/Database/Queries.py
OpenSTRAN/projectFiles/Database/Steel_Sections.db
OpenSTRAN/projectFiles/Database/__init__.py
OpenSTRAN/projectFiles/Database/__pycache__/Queries.cpython-310.pyc
OpenSTRAN/projectFiles/Database/__pycache__/__init__.cpython-310.pyc
OpenSTRAN/projectFiles/Icons/-XY.png
OpenSTRAN/projectFiles/Icons/-XZ.png
OpenSTRAN/projectFiles/Icons/-ZY.png
OpenSTRAN/projectFiles/Icons/3DFrame.ico
OpenSTRAN/projectFiles/Icons/ISO.png
OpenSTRAN/projectFiles/Icons/XY.png
OpenSTRAN/projectFiles/Icons/XZ.png
OpenSTRAN/projectFiles/Icons/ZY.png
OpenSTRAN/projectFiles/Icons/grid.png
OpenSTRAN/screens/__init__.py
OpenSTRAN/screens/distLoadInputScreen.py
OpenSTRAN/screens/memberInputScreen.py
OpenSTRAN/screens/memberResultsScreen.py
OpenSTRAN/screens/nodeInputScreen.py
OpenSTRAN/screens/nodeOutputScreen.py
OpenSTRAN/screens/plotScreen.py
OpenSTRAN/screens/pointLoadInputScreen.py
OpenSTRAN/screens/shapeScreen.py
OpenSTRAN-0.0.4.dist-info/LICENSE
OpenSTRAN-0.0.4.dist-info/METADATA
OpenSTRAN-0.0.4.dist-info/WHEEL
OpenSTRAN-0.0.4.dist-info/top_level.txt
OpenSTRAN-0.0.4.dist-info/RECORD
