Metadata-Version: 2.1
Name: OpenSTRAN
Version: 0.0.4
Summary: Open Source Structural Analysis with Python
Author-email: Xavier Montoya <openstruct@os.mozmail.com>
Project-URL: Github, https://github.com/3l-Sabio/OpenSTRAN
Classifier: Programming Language :: Python :: 3
Classifier: License :: OSI Approved :: MIT License
Classifier: Operating System :: OS Independent
Classifier: Development Status :: 3 - Alpha
Requires-Python: >=3.8
License-File: LICENSE
